LICENSE.txt
README.md
setup.cfg
setup.py
rhoova/Client.py
rhoova/__init__.py
rhoova.egg-info/PKG-INFO
rhoova.egg-info/SOURCES.txt
rhoova.egg-info/dependency_links.txt
rhoova.egg-info/requires.txt
rhoova.egg-info/top_level.txt