Metadata-Version: 2.1
Name: rhoova
Version: 0.0.39
Summary: Rhoova Client
Author: Ekinoks Software
Author-email: ali.turan@ekinokssoftware.com
License: MIT
Keywords: RHOOVA,CLIENT
Classifier: Development Status :: 3 - Alpha
Classifier: Intended Audience :: Developers
Classifier: Topic :: Software Development :: Build Tools
Classifier: License :: OSI Approved :: MIT License
Classifier: Programming Language :: Python :: 3
License-File: LICENSE.txt
